gaiaviz/SkyPatch.py
gaiaviz/__init__.py
gaiaviz-0.1.1.dist-info/LICENSE
gaiaviz-0.1.1.dist-info/METADATA
gaiaviz-0.1.1.dist-info/WHEEL
gaiaviz-0.1.1.dist-info/top_level.txt
gaiaviz-0.1.1.dist-info/RECORD
