Metadata-Version: 2.1
Name: gaiaviz
Version: 0.1.1
Summary: Tools for visualizing data for Gaia DR3. Created as part of Code/Astro 2022 to learn about Python package development.
Home-page: https://github.com/amasegian/gaiaviz
License: UNKNOWN
Keywords: Gaia
Platform: UNKNOWN
License-File: LICENSE
